{
	"backtrace" : 5,
	"backtraceGraph" : 
	{
		"commands" : 
		[
			"add_custom_target",
			"_qt_internal_expose_source_file_to_ide",
			"_qt_internal_process_resource",
			"qt6_add_resources",
			"qt_add_resources",
			"set_property"
		],
		"files" : 
		[
			"/home/enzoadmin/Application/Qt/6.6.0/gcc_64/lib/cmake/Qt6Core/Qt6CoreMacros.cmake",
			"app/CMakeLists.txt"
		],
		"nodes" : 
		[
			{
				"file" : 1
			},
			{
				"command" : 4,
				"file" : 1,
				"line" : 19,
				"parent" : 0
			},
			{
				"command" : 3,
				"file" : 0,
				"line" : 374,
				"parent" : 1
			},
			{
				"command" : 2,
				"file" : 0,
				"line" : 322,
				"parent" : 2
			},
			{
				"command" : 1,
				"file" : 0,
				"line" : 1914,
				"parent" : 3
			},
			{
				"command" : 0,
				"file" : 0,
				"line" : 1749,
				"parent" : 4
			},
			{
				"command" : 1,
				"file" : 0,
				"line" : 1967,
				"parent" : 3
			},
			{
				"command" : 5,
				"file" : 0,
				"line" : 1759,
				"parent" : 6
			},
			{
				"command" : 1,
				"file" : 0,
				"line" : 1967,
				"parent" : 3
			},
			{
				"command" : 5,
				"file" : 0,
				"line" : 1759,
				"parent" : 8
			},
			{
				"command" : 1,
				"file" : 0,
				"line" : 1967,
				"parent" : 3
			},
			{
				"command" : 5,
				"file" : 0,
				"line" : 1759,
				"parent" : 10
			},
			{
				"command" : 1,
				"file" : 0,
				"line" : 1967,
				"parent" : 3
			},
			{
				"command" : 5,
				"file" : 0,
				"line" : 1759,
				"parent" : 12
			},
			{
				"command" : 1,
				"file" : 0,
				"line" : 1967,
				"parent" : 3
			},
			{
				"command" : 5,
				"file" : 0,
				"line" : 1759,
				"parent" : 14
			},
			{
				"command" : 1,
				"file" : 0,
				"line" : 1967,
				"parent" : 3
			},
			{
				"command" : 5,
				"file" : 0,
				"line" : 1759,
				"parent" : 16
			},
			{
				"command" : 1,
				"file" : 0,
				"line" : 1967,
				"parent" : 3
			},
			{
				"command" : 5,
				"file" : 0,
				"line" : 1759,
				"parent" : 18
			},
			{
				"command" : 1,
				"file" : 0,
				"line" : 1967,
				"parent" : 3
			},
			{
				"command" : 5,
				"file" : 0,
				"line" : 1759,
				"parent" : 20
			},
			{
				"command" : 1,
				"file" : 0,
				"line" : 1967,
				"parent" : 3
			},
			{
				"command" : 5,
				"file" : 0,
				"line" : 1759,
				"parent" : 22
			},
			{
				"command" : 1,
				"file" : 0,
				"line" : 1967,
				"parent" : 3
			},
			{
				"command" : 5,
				"file" : 0,
				"line" : 1759,
				"parent" : 24
			},
			{
				"command" : 1,
				"file" : 0,
				"line" : 1967,
				"parent" : 3
			},
			{
				"command" : 5,
				"file" : 0,
				"line" : 1759,
				"parent" : 26
			}
		]
	},
	"id" : "GestioTacheApp_other_files::@5f5a17c01335469806cb",
	"name" : "GestioTacheApp_other_files",
	"paths" : 
	{
		"build" : "app",
		"source" : "app"
	},
	"sourceGroups" : 
	[
		{
			"name" : "",
			"sourceIndexes" : 
			[
				0,
				1,
				2,
				3,
				4,
				5,
				6,
				7,
				8,
				9,
				10,
				11
			]
		}
	],
	"sources" : 
	[
		{
			"backtrace" : 5,
			"path" : "build/app/.rcc/dataFiles.qrc",
			"sourceGroupIndex" : 0
		},
		{
			"backtrace" : 7,
			"path" : "app/dataFiles/imageFiles/logo.svg",
			"sourceGroupIndex" : 0
		},
		{
			"backtrace" : 9,
			"path" : "app/dataFiles/imageFiles/importantIcon.svg",
			"sourceGroupIndex" : 0
		},
		{
			"backtrace" : 11,
			"path" : "app/dataFiles/imageFiles/peuImportantIcon.svg",
			"sourceGroupIndex" : 0
		},
		{
			"backtrace" : 13,
			"path" : "app/dataFiles/imageFiles/urgentIcon.svg",
			"sourceGroupIndex" : 0
		},
		{
			"backtrace" : 15,
			"path" : "app/dataFiles/imageFiles/noneIcon.svg",
			"sourceGroupIndex" : 0
		},
		{
			"backtrace" : 17,
			"path" : "app/dataFiles/imageFiles/flecheDown.svg",
			"sourceGroupIndex" : 0
		},
		{
			"backtrace" : 19,
			"path" : "app/dataFiles/imageFiles/nextPreviousIcon.svg",
			"sourceGroupIndex" : 0
		},
		{
			"backtrace" : 21,
			"path" : "app/dataFiles/fontFiles/IBMPlexMono-Medium.ttf",
			"sourceGroupIndex" : 0
		},
		{
			"backtrace" : 23,
			"path" : "app/dataFiles/fontFiles/IBMPlexMono-Regular.ttf",
			"sourceGroupIndex" : 0
		},
		{
			"backtrace" : 25,
			"path" : "app/dataFiles/fontFiles/IBMPlexMono-SemiBold.ttf",
			"sourceGroupIndex" : 0
		},
		{
			"backtrace" : 27,
			"path" : "app/dataFiles/fontFiles/IBMPlexSans-Medium.ttf",
			"sourceGroupIndex" : 0
		}
	],
	"type" : "UTILITY"
}
